django_eximagination-0.8.3.dist-info/DESCRIPTION.rst
django_eximagination-0.8.3.dist-info/METADATA
django_eximagination-0.8.3.dist-info/RECORD
django_eximagination-0.8.3.dist-info/WHEEL
django_eximagination-0.8.3.dist-info/metadata.json
django_eximagination-0.8.3.dist-info/top_level.txt
eximagination/__init__.py
eximagination/apps.py
eximagination/conf.py
eximagination/defaults.py
eximagination/exceptions.py
eximagination/helpers.py
eximagination/settings.py
eximagination/tests.py
eximagination/utils.py
eximagination/templatetags/__init__.py
eximagination/templatetags/eximaginate.py
