Metadata-Version: 2.0
Name: django-eximagination
Version: 0.8.3
Summary: A Django template tag library which allows to download external images, store them locally and return the local path to locally stored image to a desired context variable
Home-page: https://github.com/barseghyanartur/django-eximagination
Author: Artur Barseghyan
Author-email: artur.barseghyan@gmail.com
License: GPL 2.0/LGPL 2.1
Keywords: eximagination,django,external images,app,python
Platform: UNKNOWN
Classifier: Framework :: Django
Classifier: Programming Language :: Python
Classifier: Programming Language :: Python :: 2.6
Classifier: Programming Language :: Python :: 2.7
Classifier: Programming Language :: Python :: 3
Classifier: Programming Language :: Python :: 3.4
Classifier: Programming Language :: Python :: 3.5
Classifier: Programming Language :: Python :: 3.6
Classifier: Development Status :: 4 - Beta
Classifier: Environment :: Web Environment
Classifier: Intended Audience :: Developers
Classifier: Operating System :: OS Independent
Requires-Dist: six
Requires-Dist: Pillow
